vision_mcp/__init__.py
vision_mcp/__main__.py
vision_mcp/client.py
vision_mcp/const.py
vision_mcp/exceptions.py
vision_mcp/server.py
vision_mcp/utils.py
vision_mcp-0.1.0.dist-info/licenses/LICENSE
vision_mcp-0.1.0.dist-info/METADATA
vision_mcp-0.1.0.dist-info/WHEEL
vision_mcp-0.1.0.dist-info/entry_points.txt
vision_mcp-0.1.0.dist-info/top_level.txt
vision_mcp-0.1.0.dist-info/RECORD
