Metadata-Version: 2.4
Name: vision-mcp
Version: 0.1.0
Summary: MCP server for image analysis using Vision Language Models
Author-email: Richard Wang <git@xmail.ing>
License-Expression: MIT
Keywords: mcp,vision,image-analysis
Classifier: Development Status :: 4 - Beta
Classifier: Intended Audience :: Developers
Classifier: Programming Language :: Python :: 3
Classifier: Programming Language :: Python :: 3.10
Requires-Python: >=3.10
License-File: LICENSE
Requires-Dist: mcp[cli]>=1.6.0
Requires-Dist: fastapi>=0.109.2
Requires-Dist: uvicorn>=0.27.1
Requires-Dist: python-dotenv>=1.0.1
Requires-Dist: pydantic>=2.6.1
Requires-Dist: requests>=2.31.0
Provides-Extra: dev
Requires-Dist: pre-commit>=3.6.2; extra == "dev"
Requires-Dist: ruff>=0.3.0; extra == "dev"
Requires-Dist: fastmcp>=0.4.1; extra == "dev"
Requires-Dist: twine>=6.1.0; extra == "dev"
Requires-Dist: build>=1.0.3; extra == "dev"
Dynamic: license-file
